seSql/__about__.py
seSql/__init__.py
seSql/sql.py
seSql/dbc/Exceptions.py
seSql/dbc/JDBC.py
seSql/dbc/ODBC.py
seSql/dbc/ODBCError.py
seSql/dbc/Utilities.py
seSql/dbc/__init__.py
seSql/dbc/jars/mssql-jdbc-12.4.2.jre8.jar
sesql-2025.5.1.dist-info/METADATA
sesql-2025.5.1.dist-info/WHEEL
sesql-2025.5.1.dist-info/top_level.txt
sesql-2025.5.1.dist-info/RECORD
