Metadata-Version: 2.4
Name: sesql
Version: 2025.5.1
Summary: CLI to enhance versioning for Python projects
Author-email: Cybernetic Innovations <github@cyberneticinnovations.com>
License: MIT License
Classifier: License :: OSI Approved :: MIT License
Requires-Python: >=3.10
Requires-Dist: JayDeBeApi~=1.2.3
Requires-Dist: pyodbc~=5.2.0
